pywe_user/__init__.py
pywe_user/pyweuser.py
pywe_user-1.0.4.dist-info/METADATA
pywe_user-1.0.4.dist-info/WHEEL
pywe_user-1.0.4.dist-info/top_level.txt
pywe_user-1.0.4.dist-info/RECORD
